forensic_doctor/__init__.py
forensic_doctor/forensic_doctor.py
forensic_doctor-1.0.0.dist-info/LICENSE
forensic_doctor-1.0.0.dist-info/METADATA
forensic_doctor-1.0.0.dist-info/WHEEL
forensic_doctor-1.0.0.dist-info/entry_points.txt
forensic_doctor-1.0.0.dist-info/top_level.txt
forensic_doctor-1.0.0.dist-info/RECORD
