Metadata-Version: 2.1
Name: forensic-doctor
Version: 1.0.0
Summary: A forensic tool for recovering deleted files from disk images.
Home-page: https://github.com/Bytebreach/forensic-doctor
Author: MrFidal
Author-email: mrfidal@proton.me
Classifier: Programming Language :: Python :: 3
Classifier: License :: OSI Approved :: MIT License
Classifier: Operating System :: OS Independent
License-File: LICENSE
Requires-Dist: pytsk3
Requires-Dist: pyewf
